<annotation>
	<folder>Tomato___Bacterial_spot_xml</folder>
	<filename>172458d3-8e11-4e75-9f39-d7e96e885108___GCREC_Bact.Sp 3071.JPG</filename>
	<path>C:\Users\tzw\Desktop\Tomato___Bacterial_spot_xml\172458d3-8e11-4e75-9f39-d7e96e885108___GCREC_Bact.Sp 3071.JPG</path>
	<source>
		<database>Unknown</database>
	</source>
	<size>
		<width>256</width>
		<height>256</height>
		<depth>3</depth>
	</size>
	<segmented>0</segmented>
	<object>
		<name>Tomato___Bacterial_spot</name>
		<pose>Unspecified</pose>
		<truncated>0</truncated>
		<difficult>0</difficult>
		<bndbox>
			<xmin>97</xmin>
			<ymin>4</ymin>
			<xmax>143</xmax>
			<ymax>36</ymax>
		</bndbox>
	</object>
	<object>
		<name>Tomato___Bacterial_spot</name>
		<pose>Unspecified</pose>
		<truncated>0</truncated>
		<difficult>0</difficult>
		<bndbox>
			<xmin>144</xmin>
			<ymin>38</ymin>
			<xmax>158</xmax>
			<ymax>58</ymax>
		</bndbox>
	</object>
	<object>
		<name>Tomato___Bacterial_spot</name>
		<pose>Unspecified</pose>
		<truncated>0</truncated>
		<difficult>0</difficult>
		<bndbox>
			<xmin>48</xmin>
			<ymin>77</ymin>
			<xmax>67</xmax>
			<ymax>90</ymax>
		</bndbox>
	</object>
	<object>
		<name>Tomato___Bacterial_spot</name>
		<pose>Unspecified</pose>
		<truncated>0</truncated>
		<difficult>0</difficult>
		<bndbox>
			<xmin>56</xmin>
			<ymin>93</ymin>
			<xmax>67</xmax>
			<ymax>102</ymax>
		</bndbox>
	</object>
	<object>
		<name>Tomato___Bacterial_spot</name>
		<pose>Unspecified</pose>
		<truncated>0</truncated>
		<difficult>0</difficult>
		<bndbox>
			<xmin>71</xmin>
			<ymin>90</ymin>
			<xmax>83</xmax>
			<ymax>96</ymax>
		</bndbox>
	</object>
	<object>
		<name>Tomato___Bacterial_spot</name>
		<pose>Unspecified</pose>
		<truncated>0</truncated>
		<difficult>0</difficult>
		<bndbox>
			<xmin>118</xmin>
			<ymin>137</ymin>
			<xmax>131</xmax>
			<ymax>145</ymax>
		</bndbox>
	</object>
	<object>
		<name>Tomato___Bacterial_spot</name>
		<pose>Unspecified</pose>
		<truncated>0</truncated>
		<difficult>0</difficult>
		<bndbox>
			<xmin>153</xmin>
			<ymin>139</ymin>
			<xmax>168</xmax>
			<ymax>147</ymax>
		</bndbox>
	</object>
	<object>
		<name>Tomato___Bacterial_spot</name>
		<pose>Unspecified</pose>
		<truncated>0</truncated>
		<difficult>0</difficult>
		<bndbox>
			<xmin>177</xmin>
			<ymin>124</ymin>
			<xmax>190</xmax>
			<ymax>134</ymax>
		</bndbox>
	</object>
	<object>
		<name>Tomato___Bacterial_spot</name>
		<pose>Unspecified</pose>
		<truncated>0</truncated>
		<difficult>0</difficult>
		<bndbox>
			<xmin>29</xmin>
			<ymin>109</ymin>
			<xmax>45</xmax>
			<ymax>117</ymax>
		</bndbox>
	</object>
</annotation>
