<annotation>
	<folder>Tomato___Late_blight</folder>
	<filename>27616ae1-2960-4aeb-a03b-91607439eaa0___RS_Late.B 5983.JPG</filename>
	<path>C:\Users\tzw\Desktop\TomatoDetection_Featured\JPEG\Tomato___Late_blight\27616ae1-2960-4aeb-a03b-91607439eaa0___RS_Late.B 5983.JPG</path>
	<source>
		<database>Unknown</database>
	</source>
	<size>
		<width>256</width>
		<height>256</height>
		<depth>3</depth>
	</size>
	<segmented>0</segmented>
	<object>
		<name>Tomato___Late_blight</name>
		<pose>Unspecified</pose>
		<truncated>0</truncated>
		<difficult>0</difficult>
		<bndbox>
			<xmin>113</xmin>
			<ymin>25</ymin>
			<xmax>233</xmax>
			<ymax>169</ymax>
		</bndbox>
	</object>
</annotation>
