<annotation>
	<folder>img_xml</folder>
	<filename>39bc5eeb-9d3c-4b0b-8602-3e6c01ae9bd4___Matt.S_CG 0741.JPG</filename>
	<path>C:\Users\tzw\Desktop\img_xml\39bc5eeb-9d3c-4b0b-8602-3e6c01ae9bd4___Matt.S_CG 0741.JPG</path>
	<source>
		<database>Unknown</database>
	</source>
	<size>
		<width>256</width>
		<height>256</height>
		<depth>3</depth>
	</size>
	<segmented>0</segmented>
	<object>
		<name>Tomato___Septoria_leaf_spot</name>
		<pose>Unspecified</pose>
		<truncated>0</truncated>
		<difficult>0</difficult>
		<bndbox>
			<xmin>111</xmin>
			<ymin>6</ymin>
			<xmax>130</xmax>
			<ymax>27</ymax>
		</bndbox>
	</object>
	<object>
		<name>Tomato___Septoria_leaf_spot</name>
		<pose>Unspecified</pose>
		<truncated>0</truncated>
		<difficult>0</difficult>
		<bndbox>
			<xmin>46</xmin>
			<ymin>71</ymin>
			<xmax>116</xmax>
			<ymax>136</ymax>
		</bndbox>
	</object>
	<object>
		<name>Tomato___Septoria_leaf_spot</name>
		<pose>Unspecified</pose>
		<truncated>0</truncated>
		<difficult>0</difficult>
		<bndbox>
			<xmin>97</xmin>
			<ymin>142</ymin>
			<xmax>113</xmax>
			<ymax>153</ymax>
		</bndbox>
	</object>
	<object>
		<name>Tomato___Septoria_leaf_spot</name>
		<pose>Unspecified</pose>
		<truncated>0</truncated>
		<difficult>0</difficult>
		<bndbox>
			<xmin>121</xmin>
			<ymin>158</ymin>
			<xmax>136</xmax>
			<ymax>169</ymax>
		</bndbox>
	</object>
	<object>
		<name>Tomato___Septoria_leaf_spot</name>
		<pose>Unspecified</pose>
		<truncated>0</truncated>
		<difficult>0</difficult>
		<bndbox>
			<xmin>149</xmin>
			<ymin>140</ymin>
			<xmax>162</xmax>
			<ymax>149</ymax>
		</bndbox>
	</object>
</annotation>
