<annotation>
	<folder>Tomato___Late_blight_remain</folder>
	<filename>46b29233-cfd6-47d0-99b5-504a4df17bbf___RS_Late.B 5350.JPG</filename>
	<path>C:\Users\tzw\Desktop\Tomato___Late_blight_remain\46b29233-cfd6-47d0-99b5-504a4df17bbf___RS_Late.B 5350.JPG</path>
	<source>
		<database>Unknown</database>
	</source>
	<size>
		<width>256</width>
		<height>256</height>
		<depth>3</depth>
	</size>
	<segmented>0</segmented>
	<object>
		<name>Tomato___Late_blight</name>
		<pose>Unspecified</pose>
		<truncated>0</truncated>
		<difficult>0</difficult>
		<bndbox>
			<xmin>136</xmin>
			<ymin>6</ymin>
			<xmax>220</xmax>
			<ymax>130</ymax>
		</bndbox>
	</object>
	<object>
		<name>Tomato___Late_blight</name>
		<pose>Unspecified</pose>
		<truncated>0</truncated>
		<difficult>0</difficult>
		<bndbox>
			<xmin>119</xmin>
			<ymin>172</ymin>
			<xmax>130</xmax>
			<ymax>180</ymax>
		</bndbox>
	</object>
	<object>
		<name>Tomato___Late_blight</name>
		<pose>Unspecified</pose>
		<truncated>0</truncated>
		<difficult>0</difficult>
		<bndbox>
			<xmin>43</xmin>
			<ymin>135</ymin>
			<xmax>57</xmax>
			<ymax>163</ymax>
		</bndbox>
	</object>
	<object>
		<name>Tomato___Late_blight</name>
		<pose>Unspecified</pose>
		<truncated>0</truncated>
		<difficult>0</difficult>
		<bndbox>
			<xmin>26</xmin>
			<ymin>167</ymin>
			<xmax>48</xmax>
			<ymax>181</ymax>
		</bndbox>
	</object>
</annotation>
