<annotation>
	<folder>Tomato___Leaf_Mold</folder>
	<filename>4fbc277e-5998-48c1-922d-c3f2e070f9d6___Crnl_L.Mold 6593.JPG</filename>
	<path>C:\Users\tzw\Desktop\Tomato___Leaf_Mold\4fbc277e-5998-48c1-922d-c3f2e070f9d6___Crnl_L.Mold 6593.JPG</path>
	<source>
		<database>Unknown</database>
	</source>
	<size>
		<width>256</width>
		<height>256</height>
		<depth>3</depth>
	</size>
	<segmented>0</segmented>
	<object>
		<name>Tomato___Leaf_Mold</name>
		<pose>Unspecified</pose>
		<truncated>0</truncated>
		<difficult>0</difficult>
		<bndbox>
			<xmin>158</xmin>
			<ymin>47</ymin>
			<xmax>174</xmax>
			<ymax>64</ymax>
		</bndbox>
	</object>
	<object>
		<name>Tomato___Leaf_Mold</name>
		<pose>Unspecified</pose>
		<truncated>0</truncated>
		<difficult>0</difficult>
		<bndbox>
			<xmin>197</xmin>
			<ymin>56</ymin>
			<xmax>220</xmax>
			<ymax>76</ymax>
		</bndbox>
	</object>
	<object>
		<name>Tomato___Leaf_Mold</name>
		<pose>Unspecified</pose>
		<truncated>0</truncated>
		<difficult>0</difficult>
		<bndbox>
			<xmin>133</xmin>
			<ymin>181</ymin>
			<xmax>156</xmax>
			<ymax>194</ymax>
		</bndbox>
	</object>
</annotation>
