<annotation>
	<folder>Tomato___Leaf_Mold</folder>
	<filename>625e4181-9290-45e1-986c-1c168d912a6d___Crnl_L.Mold 9017.JPG</filename>
	<path>C:\Users\tzw\Desktop\Tomato___Leaf_Mold\625e4181-9290-45e1-986c-1c168d912a6d___Crnl_L.Mold 9017.JPG</path>
	<source>
		<database>Unknown</database>
	</source>
	<size>
		<width>256</width>
		<height>256</height>
		<depth>3</depth>
	</size>
	<segmented>0</segmented>
	<object>
		<name>Tomato___Leaf_Mold</name>
		<pose>Unspecified</pose>
		<truncated>0</truncated>
		<difficult>0</difficult>
		<bndbox>
			<xmin>33</xmin>
			<ymin>21</ymin>
			<xmax>54</xmax>
			<ymax>33</ymax>
		</bndbox>
	</object>
	<object>
		<name>Tomato___Leaf_Mold</name>
		<pose>Unspecified</pose>
		<truncated>0</truncated>
		<difficult>0</difficult>
		<bndbox>
			<xmin>40</xmin>
			<ymin>40</ymin>
			<xmax>62</xmax>
			<ymax>54</ymax>
		</bndbox>
	</object>
	<object>
		<name>Tomato___Leaf_Mold</name>
		<pose>Unspecified</pose>
		<truncated>0</truncated>
		<difficult>0</difficult>
		<bndbox>
			<xmin>73</xmin>
			<ymin>50</ymin>
			<xmax>90</xmax>
			<ymax>63</ymax>
		</bndbox>
	</object>
	<object>
		<name>Tomato___Leaf_Mold</name>
		<pose>Unspecified</pose>
		<truncated>0</truncated>
		<difficult>0</difficult>
		<bndbox>
			<xmin>53</xmin>
			<ymin>67</ymin>
			<xmax>77</xmax>
			<ymax>90</ymax>
		</bndbox>
	</object>
	<object>
		<name>Tomato___Leaf_Mold</name>
		<pose>Unspecified</pose>
		<truncated>0</truncated>
		<difficult>0</difficult>
		<bndbox>
			<xmin>69</xmin>
			<ymin>91</ymin>
			<xmax>83</xmax>
			<ymax>111</ymax>
		</bndbox>
	</object>
	<object>
		<name>Tomato___Leaf_Mold</name>
		<pose>Unspecified</pose>
		<truncated>0</truncated>
		<difficult>0</difficult>
		<bndbox>
			<xmin>61</xmin>
			<ymin>121</ymin>
			<xmax>100</xmax>
			<ymax>143</ymax>
		</bndbox>
	</object>
	<object>
		<name>Tomato___Leaf_Mold</name>
		<pose>Unspecified</pose>
		<truncated>0</truncated>
		<difficult>0</difficult>
		<bndbox>
			<xmin>100</xmin>
			<ymin>59</ymin>
			<xmax>112</xmax>
			<ymax>70</ymax>
		</bndbox>
	</object>
</annotation>
