<annotation>
	<folder>img_xml</folder>
	<filename>6dd10d1f-99af-4292-be90-aa038682da34___Matt.S_CG 1006.JPG</filename>
	<path>C:\Users\tzw\Desktop\img_xml\6dd10d1f-99af-4292-be90-aa038682da34___Matt.S_CG 1006.JPG</path>
	<source>
		<database>Unknown</database>
	</source>
	<size>
		<width>256</width>
		<height>256</height>
		<depth>3</depth>
	</size>
	<segmented>0</segmented>
	<object>
		<name>Tomato___Septoria_leaf_spot</name>
		<pose>Unspecified</pose>
		<truncated>0</truncated>
		<difficult>0</difficult>
		<bndbox>
			<xmin>137</xmin>
			<ymin>37</ymin>
			<xmax>156</xmax>
			<ymax>49</ymax>
		</bndbox>
	</object>
	<object>
		<name>Tomato___Septoria_leaf_spot</name>
		<pose>Unspecified</pose>
		<truncated>0</truncated>
		<difficult>0</difficult>
		<bndbox>
			<xmin>178</xmin>
			<ymin>47</ymin>
			<xmax>193</xmax>
			<ymax>64</ymax>
		</bndbox>
	</object>
	<object>
		<name>Tomato___Septoria_leaf_spot</name>
		<pose>Unspecified</pose>
		<truncated>0</truncated>
		<difficult>0</difficult>
		<bndbox>
			<xmin>130</xmin>
			<ymin>55</ymin>
			<xmax>150</xmax>
			<ymax>64</ymax>
		</bndbox>
	</object>
	<object>
		<name>Tomato___Septoria_leaf_spot</name>
		<pose>Unspecified</pose>
		<truncated>0</truncated>
		<difficult>0</difficult>
		<bndbox>
			<xmin>147</xmin>
			<ymin>68</ymin>
			<xmax>157</xmax>
			<ymax>74</ymax>
		</bndbox>
	</object>
	<object>
		<name>Tomato___Septoria_leaf_spot</name>
		<pose>Unspecified</pose>
		<truncated>0</truncated>
		<difficult>0</difficult>
		<bndbox>
			<xmin>64</xmin>
			<ymin>73</ymin>
			<xmax>144</xmax>
			<ymax>105</ymax>
		</bndbox>
	</object>
	<object>
		<name>Tomato___Septoria_leaf_spot</name>
		<pose>Unspecified</pose>
		<truncated>0</truncated>
		<difficult>0</difficult>
		<bndbox>
			<xmin>143</xmin>
			<ymin>75</ymin>
			<xmax>228</xmax>
			<ymax>137</ymax>
		</bndbox>
	</object>
	<object>
		<name>Tomato___Septoria_leaf_spot</name>
		<pose>Unspecified</pose>
		<truncated>0</truncated>
		<difficult>0</difficult>
		<bndbox>
			<xmin>113</xmin>
			<ymin>106</ymin>
			<xmax>124</xmax>
			<ymax>113</ymax>
		</bndbox>
	</object>
	<object>
		<name>Tomato___Septoria_leaf_spot</name>
		<pose>Unspecified</pose>
		<truncated>0</truncated>
		<difficult>0</difficult>
		<bndbox>
			<xmin>116</xmin>
			<ymin>116</ymin>
			<xmax>125</xmax>
			<ymax>125</ymax>
		</bndbox>
	</object>
	<object>
		<name>Tomato___Septoria_leaf_spot</name>
		<pose>Unspecified</pose>
		<truncated>0</truncated>
		<difficult>0</difficult>
		<bndbox>
			<xmin>128</xmin>
			<ymin>117</ymin>
			<xmax>142</xmax>
			<ymax>126</ymax>
		</bndbox>
	</object>
	<object>
		<name>Tomato___Septoria_leaf_spot</name>
		<pose>Unspecified</pose>
		<truncated>0</truncated>
		<difficult>0</difficult>
		<bndbox>
			<xmin>131</xmin>
			<ymin>137</ymin>
			<xmax>156</xmax>
			<ymax>153</ymax>
		</bndbox>
	</object>
	<object>
		<name>Tomato___Septoria_leaf_spot</name>
		<pose>Unspecified</pose>
		<truncated>0</truncated>
		<difficult>0</difficult>
		<bndbox>
			<xmin>198</xmin>
			<ymin>144</ymin>
			<xmax>217</xmax>
			<ymax>162</ymax>
		</bndbox>
	</object>
	<object>
		<name>Tomato___Septoria_leaf_spot</name>
		<pose>Unspecified</pose>
		<truncated>0</truncated>
		<difficult>0</difficult>
		<bndbox>
			<xmin>168</xmin>
			<ymin>152</ymin>
			<xmax>180</xmax>
			<ymax>159</ymax>
		</bndbox>
	</object>
	<object>
		<name>Tomato___Septoria_leaf_spot</name>
		<pose>Unspecified</pose>
		<truncated>0</truncated>
		<difficult>0</difficult>
		<bndbox>
			<xmin>59</xmin>
			<ymin>145</ymin>
			<xmax>68</xmax>
			<ymax>152</ymax>
		</bndbox>
	</object>
	<object>
		<name>Tomato___Septoria_leaf_spot</name>
		<pose>Unspecified</pose>
		<truncated>0</truncated>
		<difficult>0</difficult>
		<bndbox>
			<xmin>70</xmin>
			<ymin>157</ymin>
			<xmax>79</xmax>
			<ymax>164</ymax>
		</bndbox>
	</object>
	<object>
		<name>Tomato___Septoria_leaf_spot</name>
		<pose>Unspecified</pose>
		<truncated>0</truncated>
		<difficult>0</difficult>
		<bndbox>
			<xmin>102</xmin>
			<ymin>157</ymin>
			<xmax>131</xmax>
			<ymax>190</ymax>
		</bndbox>
	</object>
	<object>
		<name>Tomato___Septoria_leaf_spot</name>
		<pose>Unspecified</pose>
		<truncated>0</truncated>
		<difficult>0</difficult>
		<bndbox>
			<xmin>94</xmin>
			<ymin>184</ymin>
			<xmax>107</xmax>
			<ymax>192</ymax>
		</bndbox>
	</object>
</annotation>
