<annotation>
	<folder>图片</folder>
	<filename>7f847477-1111-4f20-9de5-56153bee415b___RS_Late.B 5049.JPG</filename>
	<path>C:\Users\XIONGJINCHAO\Desktop\tupian\图片\7f847477-1111-4f20-9de5-56153bee415b___RS_Late.B 5049.JPG</path>
	<source>
		<database>Unknown</database>
	</source>
	<size>
		<width>256</width>
		<height>256</height>
		<depth>3</depth>
	</size>
	<segmented>0</segmented>
	<object>
		<name>Tomato___Late_blight</name>
		<pose>Unspecified</pose>
		<truncated>0</truncated>
		<difficult>0</difficult>
		<bndbox>
			<xmin>98</xmin>
			<ymin>6</ymin>
			<xmax>229</xmax>
			<ymax>146</ymax>
		</bndbox>
	</object>
</annotation>
