<annotation>
	<folder>Tomato___Leaf_Mold</folder>
	<filename>81a0a46e-f862-4a63-8304-e2c537ca8fb2___Crnl_L.Mold 6824.JPG</filename>
	<path>C:\Users\tzw\Desktop\Tomato___Leaf_Mold\81a0a46e-f862-4a63-8304-e2c537ca8fb2___Crnl_L.Mold 6824.JPG</path>
	<source>
		<database>Unknown</database>
	</source>
	<size>
		<width>256</width>
		<height>256</height>
		<depth>3</depth>
	</size>
	<segmented>0</segmented>
	<object>
		<name>Tomato___Leaf_Mold</name>
		<pose>Unspecified</pose>
		<truncated>0</truncated>
		<difficult>0</difficult>
		<bndbox>
			<xmin>140</xmin>
			<ymin>100</ymin>
			<xmax>189</xmax>
			<ymax>151</ymax>
		</bndbox>
	</object>
	<object>
		<name>Tomato___Leaf_Mold</name>
		<pose>Unspecified</pose>
		<truncated>0</truncated>
		<difficult>0</difficult>
		<bndbox>
			<xmin>191</xmin>
			<ymin>122</ymin>
			<xmax>208</xmax>
			<ymax>137</ymax>
		</bndbox>
	</object>
</annotation>
