<annotation>
	<folder>Tomato___Leaf_Mold</folder>
	<filename>98a11218-40d3-4c27-afda-abf73e371f01___Crnl_L.Mold 9055.JPG</filename>
	<path>C:\Users\tzw\Desktop\Tomato___Leaf_Mold\98a11218-40d3-4c27-afda-abf73e371f01___Crnl_L.Mold 9055.JPG</path>
	<source>
		<database>Unknown</database>
	</source>
	<size>
		<width>256</width>
		<height>256</height>
		<depth>3</depth>
	</size>
	<segmented>0</segmented>
	<object>
		<name>Tomato___Leaf_Mold</name>
		<pose>Unspecified</pose>
		<truncated>0</truncated>
		<difficult>0</difficult>
		<bndbox>
			<xmin>31</xmin>
			<ymin>114</ymin>
			<xmax>58</xmax>
			<ymax>143</ymax>
		</bndbox>
	</object>
	<object>
		<name>Tomato___Leaf_Mold</name>
		<pose>Unspecified</pose>
		<truncated>0</truncated>
		<difficult>0</difficult>
		<bndbox>
			<xmin>86</xmin>
			<ymin>157</ymin>
			<xmax>115</xmax>
			<ymax>176</ymax>
		</bndbox>
	</object>
	<object>
		<name>Tomato___Leaf_Mold</name>
		<pose>Unspecified</pose>
		<truncated>0</truncated>
		<difficult>0</difficult>
		<bndbox>
			<xmin>142</xmin>
			<ymin>158</ymin>
			<xmax>162</xmax>
			<ymax>179</ymax>
		</bndbox>
	</object>
	<object>
		<name>Tomato___Leaf_Mold</name>
		<pose>Unspecified</pose>
		<truncated>0</truncated>
		<difficult>0</difficult>
		<bndbox>
			<xmin>217</xmin>
			<ymin>149</ymin>
			<xmax>235</xmax>
			<ymax>167</ymax>
		</bndbox>
	</object>
	<object>
		<name>Tomato___Leaf_Mold</name>
		<pose>Unspecified</pose>
		<truncated>0</truncated>
		<difficult>0</difficult>
		<bndbox>
			<xmin>191</xmin>
			<ymin>156</ymin>
			<xmax>203</xmax>
			<ymax>179</ymax>
		</bndbox>
	</object>
	<object>
		<name>Tomato___Leaf_Mold</name>
		<pose>Unspecified</pose>
		<truncated>0</truncated>
		<difficult>0</difficult>
		<bndbox>
			<xmin>163</xmin>
			<ymin>219</ymin>
			<xmax>184</xmax>
			<ymax>242</ymax>
		</bndbox>
	</object>
</annotation>
