<annotation>
	<folder>图片</folder>
	<filename>9bb49d22-976d-40c3-bc9a-bff5cbbd8e28___RS_Late.B 5057.JPG</filename>
	<path>C:\Users\XIONGJINCHAO\Desktop\tupian\图片\9bb49d22-976d-40c3-bc9a-bff5cbbd8e28___RS_Late.B 5057.JPG</path>
	<source>
		<database>Unknown</database>
	</source>
	<size>
		<width>256</width>
		<height>256</height>
		<depth>3</depth>
	</size>
	<segmented>0</segmented>
	<object>
		<name>Tomato___Late_blight</name>
		<pose>Unspecified</pose>
		<truncated>0</truncated>
		<difficult>0</difficult>
		<bndbox>
			<xmin>19</xmin>
			<ymin>31</ymin>
			<xmax>199</xmax>
			<ymax>162</ymax>
		</bndbox>
	</object>
</annotation>
