<annotation>
	<folder>Tomato___Late_blight_half1</folder>
	<filename>a5d9410b-4ca9-494f-ba13-c7a01c48fa49___RS_Late.B 7147.JPG</filename>
	<path>E:\temp\Tomato___Late_blight_half1\a5d9410b-4ca9-494f-ba13-c7a01c48fa49___RS_Late.B 7147.JPG</path>
	<source>
		<database>Unknown</database>
	</source>
	<size>
		<width>256</width>
		<height>256</height>
		<depth>3</depth>
	</size>
	<segmented>0</segmented>
	<object>
		<name>Tomato___Late_blight</name>
		<pose>Unspecified</pose>
		<truncated>0</truncated>
		<difficult>0</difficult>
		<bndbox>
			<xmin>108</xmin>
			<ymin>17</ymin>
			<xmax>232</xmax>
			<ymax>151</ymax>
		</bndbox>
	</object>
</annotation>
