<annotation>
	<folder>Tomato___Late_blight</folder>
	<filename>b3cc95da-557b-456d-9c5d-2ba5d9eb0e98___RS_Late.B 4930.JPG</filename>
	<path>C:\Users\tzw\Desktop\TomatoDetection_Featured\JPEG\Tomato___Late_blight\b3cc95da-557b-456d-9c5d-2ba5d9eb0e98___RS_Late.B 4930.JPG</path>
	<source>
		<database>Unknown</database>
	</source>
	<size>
		<width>256</width>
		<height>256</height>
		<depth>3</depth>
	</size>
	<segmented>0</segmented>
	<object>
		<name>Tomato___Late_blight</name>
		<pose>Unspecified</pose>
		<truncated>0</truncated>
		<difficult>0</difficult>
		<bndbox>
			<xmin>119</xmin>
			<ymin>64</ymin>
			<xmax>215</xmax>
			<ymax>135</ymax>
		</bndbox>
	</object>
</annotation>
