<annotation>
	<folder>Tomato___Early_blight</folder>
	<filename>efb0d54f-53c7-4a6a-a194-2bd449799c8c___RS_Erly.B 7726.JPG</filename>
	<path>C:\Users\tzw\Desktop\Tomato___Early_blight\efb0d54f-53c7-4a6a-a194-2bd449799c8c___RS_Erly.B 7726.JPG</path>
	<source>
		<database>Unknown</database>
	</source>
	<size>
		<width>256</width>
		<height>256</height>
		<depth>3</depth>
	</size>
	<segmented>0</segmented>
	<object>
		<name>Tomato___Early_blight</name>
		<pose>Unspecified</pose>
		<truncated>0</truncated>
		<difficult>0</difficult>
		<bndbox>
			<xmin>15</xmin>
			<ymin>164</ymin>
			<xmax>128</xmax>
			<ymax>237</ymax>
		</bndbox>
	</object>
	<object>
		<name>Tomato___Early_blight</name>
		<pose>Unspecified</pose>
		<truncated>0</truncated>
		<difficult>0</difficult>
		<bndbox>
			<xmin>59</xmin>
			<ymin>139</ymin>
			<xmax>95</xmax>
			<ymax>164</ymax>
		</bndbox>
	</object>
	<object>
		<name>Tomato___Early_blight</name>
		<pose>Unspecified</pose>
		<truncated>0</truncated>
		<difficult>0</difficult>
		<bndbox>
			<xmin>146</xmin>
			<ymin>183</ymin>
			<xmax>213</xmax>
			<ymax>222</ymax>
		</bndbox>
	</object>
	<object>
		<name>Tomato___Early_blight</name>
		<pose>Unspecified</pose>
		<truncated>0</truncated>
		<difficult>0</difficult>
		<bndbox>
			<xmin>210</xmin>
			<ymin>131</ymin>
			<xmax>226</xmax>
			<ymax>147</ymax>
		</bndbox>
	</object>
	<object>
		<name>Tomato___Early_blight</name>
		<pose>Unspecified</pose>
		<truncated>0</truncated>
		<difficult>0</difficult>
		<bndbox>
			<xmin>191</xmin>
			<ymin>143</ymin>
			<xmax>238</xmax>
			<ymax>170</ymax>
		</bndbox>
	</object>
</annotation>
