<annotation>
	<folder>Tomato___Leaf_Mold</folder>
	<filename>f4844fb4-c16b-454b-b5b2-64911885ec71___Crnl_L.Mold 8657.JPG</filename>
	<path>C:\Users\tzw\Desktop\Tomato___Leaf_Mold\f4844fb4-c16b-454b-b5b2-64911885ec71___Crnl_L.Mold 8657.JPG</path>
	<source>
		<database>Unknown</database>
	</source>
	<size>
		<width>256</width>
		<height>256</height>
		<depth>3</depth>
	</size>
	<segmented>0</segmented>
	<object>
		<name>Tomato___Leaf_Mold</name>
		<pose>Unspecified</pose>
		<truncated>0</truncated>
		<difficult>0</difficult>
		<bndbox>
			<xmin>148</xmin>
			<ymin>54</ymin>
			<xmax>234</xmax>
			<ymax>208</ymax>
		</bndbox>
	</object>
	<object>
		<name>Tomato___Leaf_Mold</name>
		<pose>Unspecified</pose>
		<truncated>0</truncated>
		<difficult>0</difficult>
		<bndbox>
			<xmin>108</xmin>
			<ymin>92</ymin>
			<xmax>145</xmax>
			<ymax>145</ymax>
		</bndbox>
	</object>
	<object>
		<name>Tomato___Leaf_Mold</name>
		<pose>Unspecified</pose>
		<truncated>0</truncated>
		<difficult>0</difficult>
		<bndbox>
			<xmin>85</xmin>
			<ymin>122</ymin>
			<xmax>146</xmax>
			<ymax>202</ymax>
		</bndbox>
	</object>
	<object>
		<name>Tomato___Leaf_Mold</name>
		<pose>Unspecified</pose>
		<truncated>0</truncated>
		<difficult>0</difficult>
		<bndbox>
			<xmin>113</xmin>
			<ymin>196</ymin>
			<xmax>135</xmax>
			<ymax>216</ymax>
		</bndbox>
	</object>
	<object>
		<name>Tomato___Leaf_Mold</name>
		<pose>Unspecified</pose>
		<truncated>0</truncated>
		<difficult>0</difficult>
		<bndbox>
			<xmin>103</xmin>
			<ymin>227</ymin>
			<xmax>125</xmax>
			<ymax>245</ymax>
		</bndbox>
	</object>
	<object>
		<name>Tomato___Leaf_Mold</name>
		<pose>Unspecified</pose>
		<truncated>0</truncated>
		<difficult>0</difficult>
		<bndbox>
			<xmin>64</xmin>
			<ymin>157</ymin>
			<xmax>98</xmax>
			<ymax>211</ymax>
		</bndbox>
	</object>
</annotation>
