<annotation>
	<folder>Tomato___Septoria_leaf_spot_remain</folder>
	<filename>cdf7e54e-1bc9-4107-a49c-77be805c52be___Matt.S_CG 7730.JPG</filename>
	<path>C:\Users\tzw\Desktop\Tomato___Septoria_leaf_spot_remain\cdf7e54e-1bc9-4107-a49c-77be805c52be___Matt.S_CG 7730.JPG</path>
	<source>
		<database>Unknown</database>
	</source>
	<size>
		<width>256</width>
		<height>256</height>
		<depth>3</depth>
	</size>
	<segmented>0</segmented>
	<object>
		<name>Tomato___Septoria_leaf_spot</name>
		<pose>Unspecified</pose>
		<truncated>0</truncated>
		<difficult>0</difficult>
		<bndbox>
			<xmin>51</xmin>
			<ymin>6</ymin>
			<xmax>175</xmax>
			<ymax>73</ymax>
		</bndbox>
	</object>
	<object>
		<name>Tomato___Septoria_leaf_spot</name>
		<pose>Unspecified</pose>
		<truncated>0</truncated>
		<difficult>0</difficult>
		<bndbox>
			<xmin>50</xmin>
			<ymin>72</ymin>
			<xmax>81</xmax>
			<ymax>109</ymax>
		</bndbox>
	</object>
	<object>
		<name>Tomato___Septoria_leaf_spot</name>
		<pose>Unspecified</pose>
		<truncated>0</truncated>
		<difficult>0</difficult>
		<bndbox>
			<xmin>48</xmin>
			<ymin>109</ymin>
			<xmax>60</xmax>
			<ymax>120</ymax>
		</bndbox>
	</object>
	<object>
		<name>Tomato___Septoria_leaf_spot</name>
		<pose>Unspecified</pose>
		<truncated>0</truncated>
		<difficult>0</difficult>
		<bndbox>
			<xmin>24</xmin>
			<ymin>112</ymin>
			<xmax>43</xmax>
			<ymax>125</ymax>
		</bndbox>
	</object>
	<object>
		<name>Tomato___Septoria_leaf_spot</name>
		<pose>Unspecified</pose>
		<truncated>0</truncated>
		<difficult>0</difficult>
		<bndbox>
			<xmin>35</xmin>
			<ymin>135</ymin>
			<xmax>65</xmax>
			<ymax>154</ymax>
		</bndbox>
	</object>
	<object>
		<name>Tomato___Septoria_leaf_spot</name>
		<pose>Unspecified</pose>
		<truncated>0</truncated>
		<difficult>0</difficult>
		<bndbox>
			<xmin>31</xmin>
			<ymin>155</ymin>
			<xmax>65</xmax>
			<ymax>187</ymax>
		</bndbox>
	</object>
	<object>
		<name>Tomato___Septoria_leaf_spot</name>
		<pose>Unspecified</pose>
		<truncated>0</truncated>
		<difficult>0</difficult>
		<bndbox>
			<xmin>77</xmin>
			<ymin>159</ymin>
			<xmax>85</xmax>
			<ymax>168</ymax>
		</bndbox>
	</object>
	<object>
		<name>Tomato___Septoria_leaf_spot</name>
		<pose>Unspecified</pose>
		<truncated>0</truncated>
		<difficult>0</difficult>
		<bndbox>
			<xmin>70</xmin>
			<ymin>177</ymin>
			<xmax>90</xmax>
			<ymax>188</ymax>
		</bndbox>
	</object>
	<object>
		<name>Tomato___Septoria_leaf_spot</name>
		<pose>Unspecified</pose>
		<truncated>0</truncated>
		<difficult>0</difficult>
		<bndbox>
			<xmin>100</xmin>
			<ymin>73</ymin>
			<xmax>149</xmax>
			<ymax>143</ymax>
		</bndbox>
	</object>
	<object>
		<name>Tomato___Septoria_leaf_spot</name>
		<pose>Unspecified</pose>
		<truncated>0</truncated>
		<difficult>0</difficult>
		<bndbox>
			<xmin>193</xmin>
			<ymin>45</ymin>
			<xmax>233</xmax>
			<ymax>73</ymax>
		</bndbox>
	</object>
	<object>
		<name>Tomato___Septoria_leaf_spot</name>
		<pose>Unspecified</pose>
		<truncated>0</truncated>
		<difficult>0</difficult>
		<bndbox>
			<xmin>178</xmin>
			<ymin>65</ymin>
			<xmax>195</xmax>
			<ymax>80</ymax>
		</bndbox>
	</object>
	<object>
		<name>Tomato___Septoria_leaf_spot</name>
		<pose>Unspecified</pose>
		<truncated>0</truncated>
		<difficult>0</difficult>
		<bndbox>
			<xmin>186</xmin>
			<ymin>80</ymin>
			<xmax>202</xmax>
			<ymax>92</ymax>
		</bndbox>
	</object>
	<object>
		<name>Tomato___Septoria_leaf_spot</name>
		<pose>Unspecified</pose>
		<truncated>0</truncated>
		<difficult>0</difficult>
		<bndbox>
			<xmin>232</xmin>
			<ymin>82</ymin>
			<xmax>244</xmax>
			<ymax>101</ymax>
		</bndbox>
	</object>
	<object>
		<name>Tomato___Septoria_leaf_spot</name>
		<pose>Unspecified</pose>
		<truncated>0</truncated>
		<difficult>0</difficult>
		<bndbox>
			<xmin>183</xmin>
			<ymin>94</ymin>
			<xmax>228</xmax>
			<ymax>144</ymax>
		</bndbox>
	</object>
	<object>
		<name>Tomato___Septoria_leaf_spot</name>
		<pose>Unspecified</pose>
		<truncated>0</truncated>
		<difficult>0</difficult>
		<bndbox>
			<xmin>107</xmin>
			<ymin>134</ymin>
			<xmax>203</xmax>
			<ymax>198</ymax>
		</bndbox>
	</object>
</annotation>
