<annotation>
	<folder>Tomato___Leaf_Mold</folder>
	<filename>ceece521-8e6b-4f7b-b4bb-54369494e7a3___Crnl_L.Mold 6931.JPG</filename>
	<path>C:\Users\tzw\Desktop\Tomato___Leaf_Mold\ceece521-8e6b-4f7b-b4bb-54369494e7a3___Crnl_L.Mold 6931.JPG</path>
	<source>
		<database>Unknown</database>
	</source>
	<size>
		<width>256</width>
		<height>256</height>
		<depth>3</depth>
	</size>
	<segmented>0</segmented>
	<object>
		<name>Tomato___Leaf_Mold</name>
		<pose>Unspecified</pose>
		<truncated>0</truncated>
		<difficult>0</difficult>
		<bndbox>
			<xmin>117</xmin>
			<ymin>13</ymin>
			<xmax>131</xmax>
			<ymax>33</ymax>
		</bndbox>
	</object>
	<object>
		<name>Tomato___Leaf_Mold</name>
		<pose>Unspecified</pose>
		<truncated>0</truncated>
		<difficult>0</difficult>
		<bndbox>
			<xmin>118</xmin>
			<ymin>55</ymin>
			<xmax>150</xmax>
			<ymax>75</ymax>
		</bndbox>
	</object>
	<object>
		<name>Tomato___Leaf_Mold</name>
		<pose>Unspecified</pose>
		<truncated>0</truncated>
		<difficult>0</difficult>
		<bndbox>
			<xmin>112</xmin>
			<ymin>78</ymin>
			<xmax>148</xmax>
			<ymax>128</ymax>
		</bndbox>
	</object>
	<object>
		<name>Tomato___Leaf_Mold</name>
		<pose>Unspecified</pose>
		<truncated>0</truncated>
		<difficult>0</difficult>
		<bndbox>
			<xmin>75</xmin>
			<ymin>125</ymin>
			<xmax>140</xmax>
			<ymax>176</ymax>
		</bndbox>
	</object>
</annotation>
