<annotation>
	<folder>Tomato___Late_blight_half1</folder>
	<filename>dd52a1b4-1d20-4417-96c9-48baac62f15b___RS_Late.B 5202.JPG</filename>
	<path>E:\temp\Tomato___Late_blight_half1\dd52a1b4-1d20-4417-96c9-48baac62f15b___RS_Late.B 5202.JPG</path>
	<source>
		<database>Unknown</database>
	</source>
	<size>
		<width>256</width>
		<height>256</height>
		<depth>3</depth>
	</size>
	<segmented>0</segmented>
	<object>
		<name>Tomato___Late_blight</name>
		<pose>Unspecified</pose>
		<truncated>0</truncated>
		<difficult>0</difficult>
		<bndbox>
			<xmin>75</xmin>
			<ymin>10</ymin>
			<xmax>253</xmax>
			<ymax>161</ymax>
		</bndbox>
	</object>
	<object>
		<name>Tomato___Late_blight</name>
		<pose>Unspecified</pose>
		<truncated>0</truncated>
		<difficult>0</difficult>
		<bndbox>
			<xmin>47</xmin>
			<ymin>162</ymin>
			<xmax>75</xmax>
			<ymax>186</ymax>
		</bndbox>
	</object>
</annotation>
